{"cameraMode":{"drawMode":0,"name":"Shaded","section":"Shading Mode"},"sceneLighting":true,"audioPlay":false,"sceneViewState":{"showFog":true,"showMaterialUpdate":false,"showSkybox":true,"showFlares":true,"showImageEffects":true,"showParticleSystems":true},"in2DMode":false,"pivot":{"x":-956.3467407226563,"y":2.1712465286254885,"z":881.9459228515625},"rotation":{"x":0.1869737207889557,"y":-0.7266063094139099,"z":0.21761977672576905,"w":0.6242809891700745},"size":1.9060168266296387,"orthographic":false}